{"players": {"1": {"name": "Aouali", "f_name": "Youcef", "gender": "30-06-1994", "birthdate": "M", "age": "27", "score": "0", "ranking": "1"}, "2": {"name": "Chagne", "f_name": "Laura", "gender": "19-04-1995", "birthdate": "F", "age": "26", "score": "0", "ranking": "2"}, "3": {"name": "Machin", "f_name": "Hubert", "gender": "01-01-2001", "birthdate": "M", "age": "20", "score": "0", "ranking": "3"}, "4": {"name": "Adesanya", "f_name": "Israel", "gender": "01-01-1989", "birthdate": "M", "age": "32", "score": "0", "ranking": "4"}, "5": {"name": "Nunes", "f_name": "Amanda", "gender": "01-01-1988", "birthdate": "F", "age": "33", "score": "0", "ranking": "5"}, "6": {"name": "Ngannou", "f_name": "Francis", "gender": "01-01-1986", "birthdate": "m", "age": "35", "score": "0", "ranking": "6"}, "7": {"name": "Moreno", "f_name": "Brandon", "gender": "01-01-1993", "birthdate": "M", "age": "28", "score": "0", "ranking": "7"}, "8": {"name": "Usman", "f_name": "Kamaru", "gender": "01-01-1987", "birthdate": "M", "age": "34", "score": "0", "ranking": "8"}, "9": {"name": "VanVeber", "f_name": "Karl", "gender": "01-01-1981", "birthdate": "M", "age": "40", "score": "0", "ranking": "10"}, "10": {"name": "chapo", "f_name": "chapi", "gender": "01-01-2020", "birthdate": "F", "age": "1", "score": "0", "ranking": "11"}, "11": {"name": "Truc", "f_name": "Monsieur", "gender": "05-05-1995", "birthdate": "M", "age": "26", "score": "0", "ranking": "15"}}}